BoxJellyfish-2.11.data/data/bjf/static/data.csv
bjf/BJFModel.py
bjf/Build.py
bjf/__init__.py
bjf/data.csv
bjf/utils.py
bjf/web.py
BoxJellyfish-2.11.dist-info/LICENSE
BoxJellyfish-2.11.dist-info/METADATA
BoxJellyfish-2.11.dist-info/WHEEL
BoxJellyfish-2.11.dist-info/top_level.txt
BoxJellyfish-2.11.dist-info/RECORD
